{
  "commands": {
    "bisect": {
      "help": "binary search through commits to find a bug, with safety guards",
      "name": "bisect",
      "passthrough": true
    },
    "checkout": {
      "help": "checkout a branch or ref with working-tree safety guards",
      "name": "checkout",
      "passthrough": true
    },
    "cherry-pick": {
      "help": "cherry-pick one or more commits onto HEAD with safety guards",
      "name": "cherry-pick",
      "passthrough": true
    },
    "commit": {
      "args": [
        {
          "help": "files to commit (supports hunk specs: file.go:1,3)",
          "name": "files",
          "required": false,
          "variadic": true
        }
      ],
      "flags": [
        {
          "default": [],
          "help": "commit message line; can be repeated to build multi-line messages",
          "name": "m",
          "repeatable": true,
          "short": "m",
          "type": "str"
        },
        {
          "help": "read the full commit message body from a file instead of --m flags",
          "name": "F",
          "short": "F",
          "type": "str"
        },
        {
          "help": "commit the staged files onto a different branch without switching to it",
          "name": "branch",
          "type": "str"
        },
        {
          "default": false,
          "help": "amend the current HEAD commit by replacing it with updated content",
          "name": "amend",
          "negatable": true,
          "type": "bool"
        },
        {
          "default": false,
          "help": "allow creating a commit even when no files have been changed",
          "name": "allow-empty",
          "negatable": true,
          "type": "bool"
        },
        {
          "default": [],
          "help": "add a key-value trailer line to the commit message (repeatable)",
          "name": "trailer",
          "repeatable": true,
          "type": "str"
        }
      ],
      "help": "stage and commit specified files in a single atomic operation",
      "name": "commit"
    },
    "doctor": {
      "constraints": [
        {
          "flags": [
            "diagnose",
            "fix",
            "uninstall"
          ],
          "type": "mutex"
        }
      ],
      "flags": [
        {
          "default": false,
          "help": "run all health checks and report results without fixing any issues",
          "name": "diagnose",
          "negatable": true,
          "type": "bool"
        },
        {
          "default": false,
          "help": "run all health checks and automatically repair any issues found",
          "name": "fix",
          "negatable": true,
          "type": "bool"
        },
        {
          "default": false,
          "help": "remove all safegit hooks and metadata from this repository entirely",
          "name": "uninstall",
          "negatable": true,
          "type": "bool"
        }
      ],
      "help": "run diagnostic health checks on the repository and optionally repair issues",
      "name": "doctor"
    },
    "merge": {
      "help": "merge a branch into HEAD with working-tree safety guards",
      "name": "merge",
      "passthrough": true
    },
    "pull": {
      "args": [
        {
          "help": "name of the remote repository to pull from (defaults to origin)",
          "name": "remote",
          "required": false
        },
        {
          "help": "name of the remote branch to fetch and merge into the current branch",
          "name": "branch",
          "required": false
        }
      ],
      "constraints": [
        {
          "flags": [
            "ff-only",
            "ff",
            "no-ff"
          ],
          "type": "mutex"
        }
      ],
      "flags": [
        {
          "default": false,
          "help": "fast-forward only; abort with an error if a merge commit is required",
          "name": "ff-only",
          "negatable": true,
          "type": "bool"
        },
        {
          "default": false,
          "help": "fast-forward when possible, otherwise create a merge commit automatically",
          "name": "ff",
          "negatable": true,
          "type": "bool"
        },
        {
          "default": false,
          "help": "always create a merge commit even when fast-forward is possible",
          "name": "no-ff",
          "negatable": true,
          "type": "bool"
        }
      ],
      "help": "fetch from remote and merge, defaulting to fast-forward-only mode",
      "name": "pull"
    },
    "push": {
      "args": [
        {
          "help": "name of the remote repository to push to (defaults to origin)",
          "name": "remote",
          "required": false
        }
      ],
      "constraints": [
        {
          "flags": [
            "only-head",
            "only-branches",
            "only-tags",
            "both-branches-and-tags"
          ],
          "type": "mutex"
        }
      ],
      "flags": [
        {
          "default": false,
          "help": "skip running pre-pre-push hook scripts before pushing to remote",
          "name": "no-pre-pre-push",
          "negatable": true,
          "type": "bool"
        },
        {
          "default": false,
          "help": "force push using --force-with-lease to prevent overwriting others' work",
          "name": "force-with-lease",
          "negatable": true,
          "type": "bool"
        },
        {
          "default": false,
          "help": "push only the current HEAD branch to the remote, ignoring other refs",
          "name": "only-head",
          "negatable": true,
          "type": "bool"
        },
        {
          "default": false,
          "help": "push all local branches to the remote, ignoring tags and other refs",
          "name": "only-branches",
          "negatable": true,
          "type": "bool"
        },
        {
          "default": false,
          "help": "push all local tags to the remote without pushing any branches",
          "name": "only-tags",
          "negatable": true,
          "type": "bool"
        },
        {
          "default": false,
          "help": "push all local branches and all tags to the remote in one operation",
          "name": "both-branches-and-tags",
          "negatable": true,
          "type": "bool"
        }
      ],
      "help": "push refs to remote with pre-pre-push hooks and automatic retry",
      "name": "push"
    },
    "rebase": {
      "help": "rebase current branch onto upstream with safety guards",
      "name": "rebase",
      "passthrough": true
    },
    "redo": {
      "flags": [
        {
          "default": false,
          "help": "redo across all sessions by ignoring the session ID ownership check",
          "name": "bypass-session",
          "negatable": true,
          "type": "bool"
        }
      ],
      "help": "restore the commit that undo removed, as a one-shot counterpart to undo",
      "name": "redo"
    },
    "reset": {
      "help": "reset HEAD with guards that prevent accidental --hard data loss",
      "name": "reset",
      "passthrough": true
    },
    "revert": {
      "help": "revert one or more commits creating inverse patches, with safety guards",
      "name": "revert",
      "passthrough": true
    },
    "scan": {
      "flags": [
        {
          "help": "regular expression pattern to search for across all objects in history",
          "name": "pattern",
          "type": "str"
        },
        {
          "help": "glob pattern limiting which blob file paths are included (e.g. '*.env', 'config/**')",
          "name": "scope",
          "type": "str"
        },
        {
          "help": "first commit hash to include when scanning history (mutually exclusive with --entire-history)",
          "name": "from",
          "type": "str"
        },
        {
          "default": false,
          "help": "scan all commits from the root of the repository to HEAD (mutually exclusive with --from)",
          "name": "entire-history",
          "negatable": true,
          "type": "bool"
        },
        {
          "help": "comma-separated list of match types to include: blobs,commits,tags,trailers,files (default: all)",
          "name": "target",
          "type": "str"
        }
      ],
      "help": "search git history for regex pattern matches across all objects and working tree files, scanning blobs, commit messages, tag annotations, and trailers with optional scope filtering and commit range selection",
      "name": "scan",
      "tags": [
        "json"
      ]
    },
    "undo": {
      "flags": [
        {
          "default": false,
          "help": "undo across all sessions by ignoring the session ID ownership check",
          "name": "bypass-session",
          "negatable": true,
          "type": "bool"
        }
      ],
      "help": "reverse the last commit, amend, or reword operation using the oplog",
      "name": "undo"
    },
    "unlock": {
      "args": [
        {
          "help": "the ref name (e.g. refs/heads/main) whose stale .lock file to remove",
          "name": "ref"
        }
      ],
      "help": "release a stale .lock file left behind by a crashed git process",
      "name": "unlock"
    },
    "version": {
      "help": "print safegit version, Go runtime version, and git version",
      "name": "version"
    }
  },
  "defaults": {
    "app": {
      "commands": {},
      "config": false,
      "deprecated": {},
      "env_prefix": null,
      "global_flags": [],
      "groups": {},
      "tag_contracts": {}
    },
    "arg": {
      "choices": null,
      "default": null,
      "required": true,
      "type": "str",
      "variadic": false
    },
    "command": {
      "args": [],
      "constraints": [],
      "flags": [],
      "hidden": false,
      "interactive": false,
      "passthrough": false,
      "tags": []
    },
    "flag": {
      "choices": null,
      "default": null,
      "env": null,
      "env_separator": null,
      "hidden": false,
      "negatable": null,
      "repeatable": false,
      "short": null,
      "unique": false
    },
    "group": {
      "commands": {},
      "deprecated": {},
      "groups": {},
      "hidden": false,
      "tags": []
    },
    "schema_version": 1
  },
  "deprecated": {
    "rewrite-author": "use 'safegit author rewrite' instead"
  },
  "global_flags": [
    {
      "default": false,
      "help": "suppress all informational output, only showing errors and results",
      "name": "quiet",
      "negatable": true,
      "short": "q",
      "type": "bool"
    },
    {
      "default": false,
      "help": "enable verbose output with detailed progress and diagnostic info",
      "name": "verbose",
      "negatable": true,
      "type": "bool"
    },
    {
      "default": false,
      "help": "preview what would happen without writing any changes to disk",
      "name": "dry-run",
      "negatable": true,
      "short": "n",
      "type": "bool"
    },
    {
      "default": false,
      "help": "automatically confirm all interactive prompts without asking",
      "name": "yes",
      "negatable": true,
      "short": "y",
      "type": "bool"
    },
    {
      "default": "",
      "help": "path to a custom safegit config file instead of the default location",
      "name": "config",
      "type": "str"
    },
    {
      "default": false,
      "help": "emit machine-readable JSON output to stdout instead of human text",
      "name": "json",
      "negatable": true,
      "type": "bool"
    }
  ],
  "groups": {
    "author": {
      "commands": {
        "check": {
          "flags": [
            {
              "help": "expected author and committer display name that all commits should use",
              "name": "name",
              "type": "str"
            },
            {
              "help": "expected author and committer email address that all commits should use",
              "name": "email",
              "type": "str"
            }
          ],
          "help": "check that all commits use the expected author and committer identity by scanning every commit in the repository history, reporting any deviations with the exact commit hashes and mismatched fields, and suggesting the corresponding safegit author rewrite command to fix each deviation found",
          "name": "check",
          "tags": [
            "json"
          ]
        },
        "list": {
          "help": "list all distinct author and committer identities across the entire commit history, showing name, email, role, and commit count for each unique identity — useful for auditing repositories with multiple contributors or detecting unwanted identity variations such as typos, old email addresses, or bot accounts that should be consolidated before a rewrite",
          "name": "list",
          "tags": [
            "json"
          ]
        },
        "rewrite": {
          "constraints": [
            {
              "flags": [
                "old-name",
                "new-name"
              ],
              "type": "co_required"
            },
            {
              "flags": [
                "old-email",
                "new-email"
              ],
              "type": "co_required"
            }
          ],
          "flags": [
            {
              "help": "current author or committer display name to search for and replace",
              "name": "old-name",
              "type": "str"
            },
            {
              "help": "new display name to substitute wherever the old name is found in history",
              "name": "new-name",
              "type": "str"
            },
            {
              "help": "current author or committer email address to search for and replace",
              "name": "old-email",
              "type": "str"
            },
            {
              "help": "new email address to substitute wherever the old email is found in history",
              "name": "new-email",
              "type": "str"
            }
          ],
          "help": "rewrite author and committer name or email across all commit history using git filter-branch style rewriting, replacing every occurrence of the old identity with the new one in both author and committer fields while preserving timestamps, commit messages, tree contents, and parent relationships so the rewritten history is otherwise identical to the original",
          "name": "rewrite",
          "tags": [
            "json"
          ]
        }
      },
      "help": "audit and rewrite commit author/committer identity — list all identities, check against expected values, and rewrite name or email across history",
      "name": "author"
    },
    "config": {
      "commands": {
        "get": {
          "args": [
            {
              "help": "the configuration key whose current value should be retrieved",
              "name": "key"
            }
          ],
          "help": "get the current value of a single configuration key from the .git/safegit/config.json file, printing the raw value to stdout so it can be captured by scripts or used in automation pipelines",
          "name": "get"
        },
        "set": {
          "args": [
            {
              "help": "the configuration key to set to the specified value in config.json",
              "name": "key"
            },
            {
              "help": "the new value to assign to the specified configuration key",
              "name": "value"
            }
          ],
          "help": "set a configuration key to a new value in the .git/safegit/config.json file, creating the file if it does not exist yet, and persisting the change for all future safegit invocations in this repository",
          "name": "set"
        },
        "show": {
          "help": "show all configuration values currently in effect for this repository, including built-in defaults and any user overrides from the .git/safegit/config.json file, printed as key-value pairs to stdout for inspection and debugging purposes",
          "name": "show"
        }
      },
      "help": "show, get, or set safegit configuration key-value pairs",
      "name": "config"
    },
    "hook": {
      "commands": {
        "install": {
          "args": [
            {
              "help": "filesystem path to the hook script file to install into safegit",
              "name": "path"
            }
          ],
          "help": "install a pre-pre-push hook by copying a script file into the .git/safegit/hooks directory, making it executable, and registering it so that safegit push will run it before any network I/O occurs",
          "name": "install"
        },
        "list": {
          "help": "list all pre-pre-push hooks currently installed in the .git/safegit/hooks directory, showing each hook name, file path, and whether it is executable, so you can audit which checks run before every push",
          "name": "list"
        },
        "run": {
          "args": [
            {
              "help": "name of a specific hook to run; omit to run all installed hooks",
              "name": "name",
              "required": false
            }
          ],
          "help": "run all installed pre-pre-push hooks (or a single named hook) immediately without performing an actual push, so you can verify that all configured hooks pass before committing to a real push operation",
          "name": "run"
        }
      },
      "help": "manage pre-pre-push hook scripts that run before every push",
      "name": "hook"
    },
    "scrub": {
      "commands": {
        "file": {
          "args": [
            {
              "help": "repository-relative path to the file that should be scrubbed from history",
              "name": "file"
            }
          ],
          "flags": [
            {
              "help": "first commit hash to include when rewriting history (default: root commit)",
              "name": "from",
              "type": "str"
            },
            {
              "help": "mandatory audit trail message explaining why this scrub operation is needed",
              "name": "reason",
              "type": "str"
            }
          ],
          "help": "replace or remove a specific file across all commits in the repository history, rewriting each affected commit tree to either substitute the file contents with a sanitized version or delete the file entirely from every historical snapshot",
          "name": "file",
          "tags": [
            "json"
          ]
        },
        "match": {
          "constraints": [
            {
              "flags": [
                "replace",
                "mangle"
              ],
              "type": "mutex"
            },
            {
              "flags": [
                "from",
                "entire-history"
              ],
              "type": "mutex"
            }
          ],
          "flags": [
            {
              "help": "regular expression pattern to search for across all blobs in history",
              "name": "pattern",
              "type": "str"
            },
            {
              "help": "mandatory audit trail message explaining why this scrub operation is needed",
              "name": "reason",
              "type": "str"
            },
            {
              "help": "glob pattern limiting which file paths are searched (e.g. '*.env', 'config/**')",
              "name": "scope",
              "type": "str"
            },
            {
              "help": "literal string to substitute for each regex match found in history",
              "name": "replace",
              "type": "str"
            },
            {
              "default": false,
              "help": "replace matches with random printable ASCII of same length",
              "name": "mangle",
              "negatable": true,
              "type": "bool"
            },
            {
              "help": "first commit hash to include when rewriting history (default: root commit)",
              "name": "from",
              "type": "str"
            },
            {
              "default": false,
              "help": "rewrite all commits from the root of the repository to HEAD",
              "name": "entire-history",
              "negatable": true,
              "type": "bool"
            }
          ],
          "help": "replace all occurrences of a regex pattern across every blob in the repository history, rewriting commit trees to substitute matched text with a replacement string so that sensitive values like secrets and credentials are permanently removed from all historical snapshots",
          "name": "match",
          "tags": [
            "json"
          ]
        },
        "run": {
          "args": [
            {
              "help": "path to the TOML recipe file containing scrub operations",
              "name": "recipe"
            }
          ],
          "constraints": [
            {
              "flags": [
                "from",
                "entire-history"
              ],
              "type": "mutex"
            }
          ],
          "flags": [
            {
              "help": "mandatory audit trail message explaining why this scrub operation is needed",
              "name": "reason",
              "type": "str"
            },
            {
              "default": false,
              "help": "preview what would change without modifying any objects, showing unified diffs",
              "name": "diff",
              "negatable": true,
              "type": "bool"
            },
            {
              "default": 50,
              "help": "maximum number of blob diffs to show in --diff mode (default: 50)",
              "name": "limit",
              "type": "int"
            },
            {
              "help": "first commit hash to include when rewriting history",
              "name": "from",
              "type": "str"
            },
            {
              "default": false,
              "help": "rewrite all commits from the root of the repository to HEAD",
              "name": "entire-history",
              "negatable": true,
              "type": "bool"
            }
          ],
          "help": "execute a multi-operation scrub recipe from a TOML file, applying all pattern replacements and file removals across history in a single coordinated pass with topological commit ordering, overlap detection between operations, and automatic verification that no matched content survives in the rewritten object store — use --diff to preview all changes as unified diffs before committing to the rewrite",
          "name": "run",
          "tags": [
            "json"
          ]
        },
        "verify": {
          "help": "check all scrub policies defined in the repository configuration to confirm that previously scrubbed secrets and sensitive patterns remain completely absent from every object in the git object store, scanning blobs, commit messages, and tag annotations and reporting detailed per-policy pass or fail results with match locations for any violations found",
          "name": "verify",
          "tags": [
            "json"
          ]
        }
      },
      "help": "surgically rewrite git history to remove or replace sensitive content such as secrets, credentials, and private data from all commits, trees, and blobs in the repository",
      "name": "scrub"
    }
  },
  "help": "concurrency-safe git for multi-agent use",
  "name": "safegit",
  "project_id": "github.com/smm-h/safegit",
  "schema_version": 1,
  "version": "0.21.1-0.20260629205735-caa56673105e+dirty"
}
